blpdecode/__init__.py
blpdecode/blpdecode.py
blpdecode/cli.py
blpdecode/version.py
blpdecode-0.4.4.dist-info/entry_points.txt
blpdecode-0.4.4.dist-info/LICENSE
blpdecode-0.4.4.dist-info/WHEEL
blpdecode-0.4.4.dist-info/METADATA
blpdecode-0.4.4.dist-info/RECORD
