Metadata-Version: 2.1
Name: blpdecode
Version: 0.4.4
Summary: Top-level package for blpdecode.
Keywords: blpdecode
Author-email: Matt Krueger <mkrueger@rstms.net>
Classifier: Intended Audience :: Developers
Classifier: Natural Language :: English
Classifier: Programming Language :: Python :: 3
Classifier: Programming Language :: Python :: 3.8
Classifier: Programming Language :: Python :: 3.9
Classifier: Programming Language :: Python :: 3.10
Requires-Dist: click == 8.0.3
Requires-Dist: requests == 2.27.1
Requires-Dist: black==21.11b1 ; extra == "dev"
Requires-Dist: bump2version==1.0.1 ; extra == "dev"
Requires-Dist: coverage==6.2 ; extra == "dev"
Requires-Dist: flake8==4.0.1 ; extra == "dev"
Requires-Dist: pytest==6.2.5 ; extra == "dev"
Requires-Dist: tox==3.24.4 ; extra == "dev"
Requires-Dist: sphinx==4.3.2 ; extra == "docs"
Requires-Dist: sphinx-click==3.0.2 ; extra == "docs"
Project-URL: Home, https://github.com/rstms/blpdecode
Provides-Extra: dev
Provides-Extra: docs
